{
  "men_wear": [
    {
      "id": 1,
      "name": "ultra light down vest",
      "category": "coats_and_jackets",
      "price": 499.99,
      "currency": "SEK",
      "color": "Blue",
      "size": ["S", "M", "L", "XL"],
      "quantity_sold": 30,
      "quantity_in_stock": 20
    },
    {
      "id": 2,
      "name": "seamless down 3d cut parka",
      "category": "coats_and_jackets",
      "price": 899.99,
      "currency": "SEK",
      "color": "Black",
      "size": ["M", "L", "XL"],
      "quantity_sold": 15,
      "quantity_in_stock": 10
    },
    {
      "id": 3,
      "name": "blocktech 3d cut parka",
      "category": "coats_and_jackets",
      "price": 799.99,
      "currency": "SEK",
      "color": "Gray",
      "size": ["S", "M", "L", "XL"],
      "quantity_sold": 20,
      "quantity_in_stock": 15
    },
    {
      "id": 4,
      "name": "reversible fleece-lined jacket",
      "category": "coats_and_jackets",
      "price": 699.99,
      "currency": "SEK",
      "color": "Green",
      "size": ["M", "L", "XL"],
      "quantity_sold": 10,
      "quantity_in_stock": 5
    },
    {
      "id": 5,
      "name": "waterproof hooded parka",
      "category": "coats_and_jackets",
      "price": 1299.99,
      "currency": "SEK",
      "color": "Navy",
      "size": ["S", "M", "L"],
      "quantity_sold": 25,
      "quantity_in_stock": 10
    },
    {
      "id": 6,
      "name": "100% extra fine merino crew neck jumper",
      "category": "jumpers_and_cardigans",
      "price": 349.99,
      "currency": "SEK",
      "color": "Red",
      "size": ["S", "M", "L"],
      "quantity_sold": 25,
      "quantity_in_stock": 5
    },
    {
      "id": 7,
      "name": "100% cashmere crew neck jumper",
      "category": "jumpers_and_cardigans",
      "price": 699.99,
      "currency": "SEK",
      "color": "Navy",
      "size": ["M", "L", "XL"],
      "quantity_sold": 10,
      "quantity_in_stock": 10
    },
    {
      "id": 8,
      "name": "soufflé yarn jacquard half-zipped jumper",
      "category": "jumpers_and_cardigans",
      "price": 459.99,
      "currency": "SEK",
      "color": "Green",
      "size": ["S", "M", "L"],
      "quantity_sold": 18,
      "quantity_in_stock": 7
    },
    {
      "id": 9,
      "name": "textured knit cardigan",
      "category": "jumpers_and_cardigans",
      "price": 299.99,
      "currency": "SEK",
      "color": "Brown",
      "size": ["M", "L", "XL"],
      "quantity_sold": 12,
      "quantity_in_stock": 3
    },
    {
      "id": 10,
      "name": "cable-knit half-zip sweater",
      "category": "jumpers_and_cardigans",
      "price": 379.99,
      "currency": "SEK",
      "color": "Charcoal",
      "size": ["S", "M", "L"],
      "quantity_sold": 20,
      "quantity_in_stock": 8
    },
    {
      "id": 11,
      "name": "dry colour crew neck short sleeved t-shirt",
      "category": "tops_tshirts_sweats",
      "price": 149.99,
      "currency": "SEK",
      "color": "White",
      "size": ["S", "M", "L"],
      "quantity_sold": 35,
      "quantity_in_stock": 15
    },
    {
      "id": 12,
      "name": "airsense ultra light jacket",
      "category": "tops_tshirts_sweats",
      "price": 579.99,
      "currency": "SEK",
      "color": "Black",
      "size": ["M", "L", "XL"],
      "quantity_sold": 22,
      "quantity_in_stock": 8
    },
    {
      "id": 13,
      "name": "performance hoodie",
      "category": "tops_tshirts_sweats",
      "price": 249.99,
      "currency": "SEK",
      "color": "Gray",
      "size": ["S", "M", "L"],
      "quantity_sold": 18,
      "quantity_in_stock": 12
    },
    {
      "id": 14,
      "name": "quick-dry v-neck t-shirt",
      "category": "tops_tshirts_sweats",
      "price": 99.99,
      "currency": "SEK",
      "color": "Blue",
      "size": ["M", "L", "XL"],
      "quantity_sold": 25,
      "quantity_in_stock": 5
    },
    {
      "id": 15,
      "name": "fleece-lined zip-up hoodie",
      "category": "tops_tshirts_sweats",
      "price": 349.99,
      "currency": "SEK",
      "color": "Charcoal",
      "size": ["S", "M", "L"],
      "quantity_sold": 15,
      "quantity_in_stock": 10
    },
    {
      "id": 16,
      "name": "oxford button-down shirt",
      "category": "shirts",
      "price": 199.99,
      "currency": "SEK",
      "color": "White",
      "size": ["S", "M", "L"],
      "quantity_sold": 30,
      "quantity_in_stock": 20
    },
    {
      "id": 17,
      "name": "flannel check shirt",
      "category": "shirts",
      "price": 229.99,
      "currency": "SEK",
      "color": "Red",
      "size": ["M", "L", "XL"],
      "quantity_sold": 12,
      "quantity_in_stock": 8
    },
    {
      "id": 18,
      "name": "linen blend short sleeve shirt",
      "category": "shirts",
      "price": 179.99,
      "currency": "SEK",
      "color": "Blue",
      "size": ["S", "M", "L"],
      "quantity_sold": 20,
      "quantity_in_stock": 15
    },
    {
      "id": 19,
      "name": "denim shirt",
      "category": "shirts",
      "price": 259.99,
      "currency": "SEK",
      "color": "Indigo",
      "size": ["M", "L", "XL"],
      "quantity_sold": 15,
      "quantity_in_stock": 10
    },
    {
      "id": 20,
      "name": "short sleeve linen shirt",
      "category": "shirts",
      "price": 149.99,
      "currency": "SEK",
      "color": "Beige",
      "size": ["S", "M", "L"],
      "quantity_sold": 18,
      "quantity_in_stock": 7
    },
    {
      "id": 21,
      "name": "smart wool-like ankle length trousers",
      "category": "trousers_jeans_shorts",
      "price": 299.99,
      "currency": "SEK",
      "color": "Black",
      "size": ["S", "M", "L"],
      "quantity_sold": 25,
      "quantity_in_stock": 5
    },
    {
      "id": 22,
      "name": "corduroy straight leg trousers",
      "category": "trousers_jeans_shorts",
      "price": 189.99,
      "currency": "SEK",
      "color": "Brown",
      "size": ["M", "L", "XL"],
      "quantity_sold": 10,
      "quantity_in_stock": 10
    },
    {
      "id": 23,
      "name": "slim fit denim jeans",
      "category": "trousers_jeans_shorts",
      "price": 249.99,
      "currency": "SEK",
      "color": "Dark Blue",
      "size": ["S", "M", "L"],
      "quantity_sold": 18,
      "quantity_in_stock": 7
    },
    {
      "id": 24,
      "name": "khaki chino shorts",
      "category": "trousers_jeans_shorts",
      "price": 129.99,
      "currency": "SEK",
      "color": "Khaki",
      "size": ["M", "L", "XL"],
      "quantity_sold": 12,
      "quantity_in_stock": 3
    },
    {
      "id": 25,
      "name": "cargo shorts",
      "category": "trousers_jeans_shorts",
      "price": 169.99,
      "currency": "SEK",
      "color": "Olive",
      "size": ["S", "M", "L"],
      "quantity_sold": 20,
      "quantity_in_stock": 8
    },
    {
      "id": 26,
      "name": "knitted lounge joggers",
      "category": "loungewear",
      "price": 179.99,
      "currency": "SEK",
      "color": "Gray",
      "size": ["S", "M", "L"],
      "quantity_sold": 15,
      "quantity_in_stock": 10
    },
    {
      "id": 27,
      "name": "hooded lounge sweatshirt",
      "category": "loungewear",
      "price": 219.99,
      "currency": "SEK",
      "color": "Charcoal",
      "size": ["M", "L", "XL"],
      "quantity_sold": 22,
      "quantity_in_stock": 8
    },
    {
      "id": 28,
      "name": "plush fleece lounge pants",
      "category": "loungewear",
      "price": 149.99,
      "currency": "SEK",
      "color": "Navy",
      "size": ["S", "M", "L"],
      "quantity_sold": 18,
      "quantity_in_stock": 12
    },
    {
      "id": 29,
      "name": "ribbed knit lounge cardigan",
      "category": "loungewear",
      "price": 269.99,
      "currency": "SEK",
      "color": "Burgundy",
      "size": ["M", "L", "XL"],
      "quantity_sold": 20,
      "quantity_in_stock": 15
    },
    {
      "id": 30,
      "name": "french terry lounge shorts",
      "category": "loungewear",
      "price": 129.99,
      "currency": "SEK",
      "color": "Olive",
      "size": ["S", "M", "L"],
      "quantity_sold": 25,
      "quantity_in_stock": 5
    }
  ]
}
