[
  {
    "description": "canadian pop"
  },
  {
    "description": "reggaeton flow"
  },
  {
    "description": "dance pop"
  },
  {
    "description": "pop"
  },
  {
    "description": "dfw rap"
  },
  {
    "description": "trap music"
  },
  {
    "description": "country rap"
  },
  {
    "description": "electropop"
  },
  {
    "description": "reggaeton"
  },
  {
    "description": "panamanian pop"
  },
  {
    "description": "canadian hip hop"
  },
  {
   " description": "latin"
  },
  {
    "description": "escape room"
  },
  {
   " description": "pop house"
  },
  {
    "description": "australian pop"
  },
  {
    "descriptio": "edm"
  },
  {
    "description": "atl hip hop"
  },
  {
    "description": "big room"
  },
  {
   " description": "boy band"
  },
  {
    "description": "r&b en espanol"
  },
  {
    "description": "brostep"
  }
]
